simple_email_sender/__init__.py
simple_email_sender/sender.py
simple_email_sender-0.0.3.dist-info/METADATA
simple_email_sender-0.0.3.dist-info/WHEEL
simple_email_sender-0.0.3.dist-info/top_level.txt
simple_email_sender-0.0.3.dist-info/RECORD
