Metadata-Version: 2.1
Name: simple-email-sender
Version: 0.0.3
Summary: This package provides a simple notifier sending emails
Home-page: https://gitlab.com/hjanssen/simple-email-sender
Author: Henning Janssen
Author-email: janssen@eeh.ee.ethz.ch
License: GNU General Public License v3
Keywords: simple_email_sender
Platform: UNKNOWN
Classifier: Development Status :: 3 - Alpha
Classifier: Intended Audience :: Developers
Classifier: Intended Audience :: Education
Classifier: Intended Audience :: Science/Research
Classifier: License :: OSI Approved :: GNU General Public License v3 (GPLv3)
Classifier: Natural Language :: English
Classifier: Programming Language :: Python :: 3.7
Classifier: Programming Language :: Python :: 3.8
Classifier: Programming Language :: Python :: 3.9
Classifier: Programming Language :: Python :: 3.10
Requires-Python: >=3.7
Requires-Dist: pyyaml
